leoribas_csv_converter/__init__.py
leoribas_csv_converter/converter.py
leoribas_csv_converter-0.2.0.dist-info/entry_points.txt
leoribas_csv_converter-0.2.0.dist-info/WHEEL
leoribas_csv_converter-0.2.0.dist-info/METADATA
leoribas_csv_converter-0.2.0.dist-info/RECORD
