Metadata-Version: 2.1
Name: leoribas-csv-converter
Version: 0.2.0
Summary: 
Author: Leonardo Ribas
Author-email: leo_rnm@hotmail.com
Requires-Python: >=3.9,<4.0
Classifier: Programming Language :: Python :: 3
Classifier: Programming Language :: Python :: 3.10
Classifier: Programming Language :: Python :: 3.9
Requires-Dist: click (>=8.0.3,<9.0.0)
Requires-Dist: pathlib (>=1.0.1,<2.0.0)
